sharpstock/__init__.py
sharpstock/main.py
sharpstock/sharpe_ratio.py
sharpstock/tests/test_sharpe_ratio.py
sharpstock-0.1.0.dist-info/LICENSE
sharpstock-0.1.0.dist-info/METADATA
sharpstock-0.1.0.dist-info/WHEEL
sharpstock-0.1.0.dist-info/RECORD
