Metadata-Version: 2.1
Name: sharpstock
Version: 0.1.0
Summary: A simple Python library to calculate the Sharpe Ratio of a stock.
Author: tim-hub
Author-email: tim-hub@users.noreply.github.com
Requires-Python: >=3.12,<4.0
Classifier: Programming Language :: Python :: 3
Classifier: Programming Language :: Python :: 3.12
Requires-Dist: pandas (>=2.2.3,<3.0.0)
